putio_automator/__init__.py
putio_automator/cli.py
putio_automator/db.py
putio_automator/commands/__init__.py
putio_automator/commands/account.py
putio_automator/commands/config.py
putio_automator/commands/db.py
putio_automator/commands/files.py
putio_automator/commands/torrents.py
putio_automator/commands/transfers.py
putio_automator-2.1.1.data/data/share/putio-automator/config.py.dist
putio_automator-2.1.1.dist-info/AUTHORS
putio_automator-2.1.1.dist-info/LICENSE
putio_automator-2.1.1.dist-info/METADATA
putio_automator-2.1.1.dist-info/WHEEL
putio_automator-2.1.1.dist-info/entry_points.txt
putio_automator-2.1.1.dist-info/pbr.json
putio_automator-2.1.1.dist-info/top_level.txt
putio_automator-2.1.1.dist-info/RECORD
