Metadata-Version: 2.1
Name: putio-automator
Version: 2.1.1
Summary: Automate management of torrents and files on Put.IO.
Home-page: https://github.com/datashaman/putio-automator
Author: Marlin Forbes
Author-email: marlinf@datashaman.com
License: MIT
Keywords: torrent,download,seedbox,media
Platform: UNKNOWN
Classifier: Development Status :: 4 - Beta
Classifier: Environment :: Console
Classifier: Intended Audience :: Developers
Classifier: Intended Audience :: End Users/Desktop
Classifier: License :: OSI Approved :: MIT License
Classifier: Programming Language :: Python :: 3
Classifier: Programming Language :: Python :: 3.6
Classifier: Programming Language :: Python :: 3.7
Classifier: Programming Language :: Python :: 3.8
Classifier: Topic :: Internet
Classifier: Topic :: Utilities
Requires-Dist: appdirs
Requires-Dist: click
Requires-Dist: click-log
Requires-Dist: putio.py
Requires-Dist: python-dotenv
Requires-Dist: pyyaml
Requires-Dist: watchdog
